[{"public_repos": 19, "site_admin": false, "subscriptions_url": "https://api.github.com/users/Trinea/subscriptions", "gravatar_id": "", "hireable": null, "id": 1169522, "followers_url": "https://api.github.com/users/Trinea/followers", "following_url": "https://api.github.com/users/Trinea/following{/other_user}", "blog": "http://www.trinea.cn/", "followers": 7927, "location": "HangZhou, China", "type": "User", "email": "trinea.cn@gmail.com", "bio": null, "gists_url": "https://api.github.com/users/Trinea/gists{/gist_id}", "company": "DiDi", "events_url": "https://api.github.com/users/Trinea/events{/privacy}", "html_url": "https://github.com/Trinea", "updated_at": "2016-05-10T11:46:25Z", "received_events_url": "https://api.github.com/users/Trinea/received_events", "starred_url": "https://api.github.com/users/Trinea/starred{/owner}{/repo}", "public_gists": 8, "name": "Trinea", "organizations_url": "https://api.github.com/users/Trinea/orgs", "url": "https://api.github.com/users/Trinea", "created_at": "2011-11-03T11:05:05Z", "avatar_url": "https://avatars.githubusercontent.com/u/1169522?v=3", "repos_url": "https://api.github.com/users/Trinea/repos", "following": 39, "login": "Trinea"}, {"public_repos": 41, "site_admin": false, "subscriptions_url": "https://api.github.com/users/drakeet/subscriptions", "gravatar_id": "", "hireable": true, "id": 5214214, "followers_url": "https://api.github.com/users/drakeet/followers", "following_url": "https://api.github.com/users/drakeet/following{/other_user}", "blog": "http://drakeet.me", "followers": 2157, "location": "Hangzhou, China", "type": "User", "email": "drakeet.me@gmail.com", "bio": null, "gists_url": "https://api.github.com/users/drakeet/gists{/gist_id}", "company": "Alibaba", "events_url": "https://api.github.com/users/drakeet/events{/privacy}", "html_url": "https://github.com/drakeet", "updated_at": "2016-05-08T20:21:56Z", "received_events_url": "https://api.github.com/users/drakeet/received_events", "starred_url": "https://api.github.com/users/drakeet/starred{/owner}{/repo}", "public_gists": 4, "name": "drakeet", "organizations_url": "https://api.github.com/users/drakeet/orgs", "url": "https://api.github.com/users/drakeet", "created_at": "2013-08-12T14:11:54Z", "avatar_url": "https://avatars.githubusercontent.com/u/5214214?v=3", "repos_url": "https://api.github.com/users/drakeet/repos", "following": 115, "login": "drakeet"}, {"public_repos": 52, "site_admin": false, "subscriptions_url": "https://api.github.com/users/wenshao/subscriptions", "gravatar_id": "", "hireable": true, "id": 1166785, "followers_url": "https://api.github.com/users/wenshao/followers", "following_url": "https://api.github.com/users/wenshao/following{/other_user}", "blog": "http://weibo.com/wengaotie", "followers": 1050, "location": "Hangzhou, Zhejiang, China", "type": "User", "email": "szujobs@gmail.com", "bio": null, "gists_url": "https://api.github.com/users/wenshao/gists{/gist_id}", "company": "Alibaba.com", "events_url": "https://api.github.com/users/wenshao/events{/privacy}", "html_url": "https://github.com/wenshao", "updated_at": "2016-04-16T13:24:31Z", "received_events_url": "https://api.github.com/users/wenshao/received_events", "starred_url": "https://api.github.com/users/wenshao/starred{/owner}{/repo}", "public_gists": 0, "name": "\u9ad8\u94c1", "organizations_url": "https://api.github.com/users/wenshao/orgs", "url": "https://api.github.com/users/wenshao", "created_at": "2011-11-02T08:01:20Z", "avatar_url": "https://avatars.githubusercontent.com/u/1166785?v=3", "repos_url": "https://api.github.com/users/wenshao/repos", "following": 12, "login": "wenshao"}, {"public_repos": 26, "site_admin": false, "subscriptions_url": "https://api.github.com/users/0x5e/subscriptions", "gravatar_id": "", "hireable": null, "id": 5144674, "followers_url": "https://api.github.com/users/0x5e/followers", "following_url": "https://api.github.com/users/0x5e/following{/other_user}", "blog": null, "followers": 638, "location": "China, Zhejiang, Hangzhou", "type": "User", "email": "0x5e@sina.cn", "bio": null, "gists_url": "https://api.github.com/users/0x5e/gists{/gist_id}", "company": null, "events_url": "https://api.github.com/users/0x5e/events{/privacy}", "html_url": "https://github.com/0x5e", "updated_at": "2016-04-23T09:29:09Z", "received_events_url": "https://api.github.com/users/0x5e/received_events", "starred_url": "https://api.github.com/users/0x5e/starred{/owner}{/repo}", "public_gists": 1, "name": "gaosen", "organizations_url": "https://api.github.com/users/0x5e/orgs", "url": "https://api.github.com/users/0x5e", "created_at": "2013-08-02T05:27:48Z", "avatar_url": "https://avatars.githubusercontent.com/u/5144674?v=3", "repos_url": "https://api.github.com/users/0x5e/repos", "following": 32, "login": "0x5e"}, {"public_repos": 36, "site_admin": false, "subscriptions_url": "https://api.github.com/users/wangjiegulu/subscriptions", "gravatar_id": "", "hireable": true, "id": 5423194, "followers_url": "https://api.github.com/users/wangjiegulu/followers", "following_url": "https://api.github.com/users/wangjiegulu/following{/other_user}", "blog": "http://www.cnblogs.com/tiantianbyconan/", "followers": 422, "location": "Hangzhou China", "type": "User", "email": "tiantian.china.2@gmail.com", "bio": null, "gists_url": "https://api.github.com/users/wangjiegulu/gists{/gist_id}", "company": "Alibaba,Xingren", "events_url": "https://api.github.com/users/wangjiegulu/events{/privacy}", "html_url": "https://github.com/wangjiegulu", "updated_at": "2016-05-08T04:48:03Z", "received_events_url": "https://api.github.com/users/wangjiegulu/received_events", "starred_url": "https://api.github.com/users/wangjiegulu/starred{/owner}{/repo}", "public_gists": 5, "name": "WangJie", "organizations_url": "https://api.github.com/users/wangjiegulu/orgs", "url": "https://api.github.com/users/wangjiegulu", "created_at": "2013-09-10T01:40:38Z", "avatar_url": "https://avatars.githubusercontent.com/u/5423194?v=3", "repos_url": "https://api.github.com/users/wangjiegulu/repos", "following": 0, "login": "wangjiegulu"}, {"public_repos": 61, "site_admin": false, "subscriptions_url": "https://api.github.com/users/DreaminginCodeZH/subscriptions", "gravatar_id": "", "hireable": true, "id": 4469895, "followers_url": "https://api.github.com/users/DreaminginCodeZH/followers", "following_url": "https://api.github.com/users/DreaminginCodeZH/following{/other_user}", "blog": "http://blog.zhanghai.me", "followers": 400, "location": "Hangzhou, Zhejiang", "type": "User", "email": null, "bio": null, "gists_url": "https://api.github.com/users/DreaminginCodeZH/gists{/gist_id}", "company": "Zhejiang University", "events_url": "https://api.github.com/users/DreaminginCodeZH/events{/privacy}", "html_url": "https://github.com/DreaminginCodeZH", "updated_at": "2016-05-09T02:47:21Z", "received_events_url": "https://api.github.com/users/DreaminginCodeZH/received_events", "starred_url": "https://api.github.com/users/DreaminginCodeZH/starred{/owner}{/repo}", "public_gists": 10, "name": "Zhang Hai", "organizations_url": "https://api.github.com/users/DreaminginCodeZH/orgs", "url": "https://api.github.com/users/DreaminginCodeZH", "created_at": "2013-05-19T09:25:59Z", "avatar_url": "https://avatars.githubusercontent.com/u/4469895?v=3", "repos_url": "https://api.github.com/users/DreaminginCodeZH/repos", "following": 59, "login": "DreaminginCodeZH"}, {"public_repos": 67, "site_admin": false, "subscriptions_url": "https://api.github.com/users/AlanCheen/subscriptions", "gravatar_id": "", "hireable": null, "id": 6982439, "followers_url": "https://api.github.com/users/AlanCheen/followers", "following_url": "https://api.github.com/users/AlanCheen/following{/other_user}", "blog": "http://yifeiyuan.me", "followers": 370, "location": "HangZhou,ZheJiang,China", "type": "User", "email": "alancheen06@gmail.com", "bio": null, "gists_url": "https://api.github.com/users/AlanCheen/gists{/gist_id}", "company": null, "events_url": "https://api.github.com/users/AlanCheen/events{/privacy}", "html_url": "https://github.com/AlanCheen", "updated_at": "2016-03-30T14:26:00Z", "received_events_url": "https://api.github.com/users/AlanCheen/received_events", "starred_url": "https://api.github.com/users/AlanCheen/starred{/owner}{/repo}", "public_gists": 1, "name": "\u7a0b\u5e8f\u4ea6\u975e\u733f", "organizations_url": "https://api.github.com/users/AlanCheen/orgs", "url": "https://api.github.com/users/AlanCheen", "created_at": "2014-03-18T02:39:03Z", "avatar_url": "https://avatars.githubusercontent.com/u/6982439?v=3", "repos_url": "https://api.github.com/users/AlanCheen/repos", "following": 70, "login": "AlanCheen"}, {"public_repos": 48, "site_admin": false, "subscriptions_url": "https://api.github.com/users/geminiwen/subscriptions", "gravatar_id": "", "hireable": true, "id": 1413056, "followers_url": "https://api.github.com/users/geminiwen/followers", "following_url": "https://api.github.com/users/geminiwen/following{/other_user}", "blog": "http://segmentfault.com/u/gemini", "followers": 297, "location": "Hangzhou,Zhejiang,CN", "type": "User", "email": "geminiwen@aliyun.com", "bio": null, "gists_url": "https://api.github.com/users/geminiwen/gists{/gist_id}", "company": "SegmentFault", "events_url": "https://api.github.com/users/geminiwen/events{/privacy}", "html_url": "https://github.com/geminiwen", "updated_at": "2016-05-11T13:36:03Z", "received_events_url": "https://api.github.com/users/geminiwen/received_events", "starred_url": "https://api.github.com/users/geminiwen/starred{/owner}{/repo}", "public_gists": 6, "name": "Gemini Wen", "organizations_url": "https://api.github.com/users/geminiwen/orgs", "url": "https://api.github.com/users/geminiwen", "created_at": "2012-02-06T16:12:21Z", "avatar_url": "https://avatars.githubusercontent.com/u/1413056?v=3", "repos_url": "https://api.github.com/users/geminiwen/repos", "following": 24, "login": "geminiwen"}, {"public_repos": 119, "site_admin": false, "subscriptions_url": "https://api.github.com/users/linux-china/subscriptions", "gravatar_id": "", "hireable": null, "id": 46711, "followers_url": "https://api.github.com/users/linux-china/followers", "following_url": "https://api.github.com/users/linux-china/following{/other_user}", "blog": "http://jenv.io", "followers": 251, "location": "Hangzhou, China", "type": "User", "email": "linux_china@hotmail.com", "bio": null, "gists_url": "https://api.github.com/users/linux-china/gists{/gist_id}", "company": null, "events_url": "https://api.github.com/users/linux-china/events{/privacy}", "html_url": "https://github.com/linux-china", "updated_at": "2016-05-12T04:04:47Z", "received_events_url": "https://api.github.com/users/linux-china/received_events", "starred_url": "https://api.github.com/users/linux-china/starred{/owner}{/repo}", "public_gists": 9, "name": "Jacky Chan", "organizations_url": "https://api.github.com/users/linux-china/orgs", "url": "https://api.github.com/users/linux-china", "created_at": "2009-01-15T04:37:59Z", "avatar_url": "https://avatars.githubusercontent.com/u/46711?v=3", "repos_url": "https://api.github.com/users/linux-china/repos", "following": 13, "login": "linux-china"}, {"public_repos": 11, "site_admin": false, "subscriptions_url": "https://api.github.com/users/xmuSistone/subscriptions", "gravatar_id": "", "hireable": true, "id": 12167762, "followers_url": "https://api.github.com/users/xmuSistone/followers", "following_url": "https://api.github.com/users/xmuSistone/following{/other_user}", "blog": "http://xmusistone.github.io/", "followers": 247, "location": "Hangzhou, Zhejiang, China", "type": "User", "email": "120809170@qq.com", "bio": null, "gists_url": "https://api.github.com/users/xmuSistone/gists{/gist_id}", "company": null, "events_url": "https://api.github.com/users/xmuSistone/events{/privacy}", "html_url": "https://github.com/xmuSistone", "updated_at": "2016-04-28T16:11:51Z", "received_events_url": "https://api.github.com/users/xmuSistone/received_events", "starred_url": "https://api.github.com/users/xmuSistone/starred{/owner}{/repo}", "public_gists": 0, "name": "stone", "organizations_url": "https://api.github.com/users/xmuSistone/orgs", "url": "https://api.github.com/users/xmuSistone", "created_at": "2015-04-29T09:29:39Z", "avatar_url": "https://avatars.githubusercontent.com/u/12167762?v=3", "repos_url": "https://api.github.com/users/xmuSistone/repos", "following": 34, "login": "xmuSistone"}, {"public_repos": 28, "site_admin": false, "subscriptions_url": "https://api.github.com/users/javachen/subscriptions", "gravatar_id": "", "hireable": null, "id": 826932, "followers_url": "https://api.github.com/users/javachen/followers", "following_url": "https://api.github.com/users/javachen/following{/other_user}", "blog": "http://blog.javachen.com", "followers": 218, "location": "Hangzhou,China", "type": "User", "email": "junezchen@gmail.com", "bio": null, "gists_url": "https://api.github.com/users/javachen/gists{/gist_id}", "company": "Alibaba", "events_url": "https://api.github.com/users/javachen/events{/privacy}", "html_url": "https://github.com/javachen", "updated_at": "2016-03-31T07:29:49Z", "received_events_url": "https://api.github.com/users/javachen/received_events", "starred_url": "https://api.github.com/users/javachen/starred{/owner}{/repo}", "public_gists": 4, "name": "javachen", "organizations_url": "https://api.github.com/users/javachen/orgs", "url": "https://api.github.com/users/javachen", "created_at": "2011-06-03T06:51:39Z", "avatar_url": "https://avatars.githubusercontent.com/u/826932?v=3", "repos_url": "https://api.github.com/users/javachen/repos", "following": 106, "login": "javachen"}, {"public_repos": 39, "site_admin": false, "subscriptions_url": "https://api.github.com/users/wwsun/subscriptions", "gravatar_id": "", "hireable": true, "id": 6984035, "followers_url": "https://api.github.com/users/wwsun/followers", "following_url": "https://api.github.com/users/wwsun/following{/other_user}", "blog": "http://wwsun.github.io", "followers": 213, "location": "Hangzhou, China", "type": "User", "email": "ww.sun@outlook.com", "bio": null, "gists_url": "https://api.github.com/users/wwsun/gists{/gist_id}", "company": "Alibaba Inc.", "events_url": "https://api.github.com/users/wwsun/events{/privacy}", "html_url": "https://github.com/wwsun", "updated_at": "2016-05-11T12:50:23Z", "received_events_url": "https://api.github.com/users/wwsun/received_events", "starred_url": "https://api.github.com/users/wwsun/starred{/owner}{/repo}", "public_gists": 13, "name": "Weiwei SUN", "organizations_url": "https://api.github.com/users/wwsun/orgs", "url": "https://api.github.com/users/wwsun", "created_at": "2014-03-18T06:37:29Z", "avatar_url": "https://avatars.githubusercontent.com/u/6984035?v=3", "repos_url": "https://api.github.com/users/wwsun/repos", "following": 39, "login": "wwsun"}, {"public_repos": 14, "site_admin": false, "subscriptions_url": "https://api.github.com/users/feicien/subscriptions", "gravatar_id": "", "hireable": true, "id": 1282265, "followers_url": "https://api.github.com/users/feicien/followers", "following_url": "https://api.github.com/users/feicien/following{/other_user}", "blog": "http://my.eoe.cn/isnull", "followers": 164, "location": "Hangzhou, China", "type": "User", "email": "ithcheng@gmail.com", "bio": null, "gists_url": "https://api.github.com/users/feicien/gists{/gist_id}", "company": "\u4e01\u9999\u56ed", "events_url": "https://api.github.com/users/feicien/events{/privacy}", "html_url": "https://github.com/feicien", "updated_at": "2016-04-22T18:52:51Z", "received_events_url": "https://api.github.com/users/feicien/received_events", "starred_url": "https://api.github.com/users/feicien/starred{/owner}{/repo}", "public_gists": 3, "name": "\u7a0b\u8f89", "organizations_url": "https://api.github.com/users/feicien/orgs", "url": "https://api.github.com/users/feicien", "created_at": "2011-12-23T14:30:52Z", "avatar_url": "https://avatars.githubusercontent.com/u/1282265?v=3", "repos_url": "https://api.github.com/users/feicien/repos", "following": 181, "login": "feicien"}, {"public_repos": 200, "site_admin": false, "subscriptions_url": "https://api.github.com/users/nuptboyzhb/subscriptions", "gravatar_id": "", "hireable": true, "id": 3404781, "followers_url": "https://api.github.com/users/nuptboyzhb/followers", "following_url": "https://api.github.com/users/nuptboyzhb/following{/other_user}", "blog": "http://www.mobctrl.net", "followers": 156, "location": "Hangzhou,Zhejiang,China", "type": "User", "email": "zhb931706659@126.com", "bio": null, "gists_url": "https://api.github.com/users/nuptboyzhb/gists{/gist_id}", "company": "Alibaba Group", "events_url": "https://api.github.com/users/nuptboyzhb/events{/privacy}", "html_url": "https://github.com/nuptboyzhb", "updated_at": "2016-04-03T12:28:08Z", "received_events_url": "https://api.github.com/users/nuptboyzhb/received_events", "starred_url": "https://api.github.com/users/nuptboyzhb/starred{/owner}{/repo}", "public_gists": 1, "name": "Zheng Haibo(\u83ab\u5ddd)", "organizations_url": "https://api.github.com/users/nuptboyzhb/orgs", "url": "https://api.github.com/users/nuptboyzhb", "created_at": "2013-01-28T10:33:16Z", "avatar_url": "https://avatars.githubusercontent.com/u/3404781?v=3", "repos_url": "https://api.github.com/users/nuptboyzhb/repos", "following": 85, "login": "nuptboyzhb"}, {"public_repos": 8, "site_admin": false, "subscriptions_url": "https://api.github.com/users/jlusdy/subscriptions", "gravatar_id": "", "hireable": null, "id": 365614, "followers_url": "https://api.github.com/users/jlusdy/followers", "following_url": "https://api.github.com/users/jlusdy/following{/other_user}", "blog": "http://reader.im/", "followers": 152, "location": "hangzhou,china", "type": "User", "email": "jlusdy@gmail.com", "bio": null, "gists_url": "https://api.github.com/users/jlusdy/gists{/gist_id}", "company": "taobao", "events_url": "https://api.github.com/users/jlusdy/events{/privacy}", "html_url": "https://github.com/jlusdy", "updated_at": "2016-04-26T11:40:23Z", "received_events_url": "https://api.github.com/users/jlusdy/received_events", "starred_url": "https://api.github.com/users/jlusdy/starred{/owner}{/repo}", "public_gists": 3, "name": "\u4e01\u5b87", "organizations_url": "https://api.github.com/users/jlusdy/orgs", "url": "https://api.github.com/users/jlusdy", "created_at": "2010-08-16T07:19:25Z", "avatar_url": "https://avatars.githubusercontent.com/u/365614?v=3", "repos_url": "https://api.github.com/users/jlusdy/repos", "following": 29, "login": "jlusdy"}, {"public_repos": 19, "site_admin": false, "subscriptions_url": "https://api.github.com/users/linyiqun/subscriptions", "gravatar_id": "", "hireable": null, "id": 7877836, "followers_url": "https://api.github.com/users/linyiqun/followers", "following_url": "https://api.github.com/users/linyiqun/following{/other_user}", "blog": "http://blog.csdn.net/androidlushangderen", "followers": 149, "location": "Hangzhou, Zhejiang, China", "type": "User", "email": null, "bio": null, "gists_url": "https://api.github.com/users/linyiqun/gists{/gist_id}", "company": "mogujie", "events_url": "https://api.github.com/users/linyiqun/events{/privacy}", "html_url": "https://github.com/linyiqun", "updated_at": "2016-04-07T11:24:07Z", "received_events_url": "https://api.github.com/users/linyiqun/received_events", "starred_url": "https://api.github.com/users/linyiqun/starred{/owner}{/repo}", "public_gists": 0, "name": "lyq", "organizations_url": "https://api.github.com/users/linyiqun/orgs", "url": "https://api.github.com/users/linyiqun", "created_at": "2014-06-13T06:53:45Z", "avatar_url": "https://avatars.githubusercontent.com/u/7877836?v=3", "repos_url": "https://api.github.com/users/linyiqun/repos", "following": 8, "login": "linyiqun"}, {"public_repos": 31, "site_admin": false, "subscriptions_url": "https://api.github.com/users/kongnanlive/subscriptions", "gravatar_id": "", "hireable": null, "id": 2374686, "followers_url": "https://api.github.com/users/kongnanlive/followers", "following_url": "https://api.github.com/users/kongnanlive/following{/other_user}", "blog": "http://weibo.com/kongnan", "followers": 134, "location": "Hangzhou, China", "type": "User", "email": "kongnanlive@gmail.com", "bio": null, "gists_url": "https://api.github.com/users/kongnanlive/gists{/gist_id}", "company": "NetEase", "events_url": "https://api.github.com/users/kongnanlive/events{/privacy}", "html_url": "https://github.com/kongnanlive", "updated_at": "2016-02-27T03:34:47Z", "received_events_url": "https://api.github.com/users/kongnanlive/received_events", "starred_url": "https://api.github.com/users/kongnanlive/starred{/owner}{/repo}", "public_gists": 0, "name": "\u5b54\u6960", "organizations_url": "https://api.github.com/users/kongnanlive/orgs", "url": "https://api.github.com/users/kongnanlive", "created_at": "2012-09-19T00:39:14Z", "avatar_url": "https://avatars.githubusercontent.com/u/2374686?v=3", "repos_url": "https://api.github.com/users/kongnanlive/repos", "following": 20, "login": "kongnanlive"}, {"public_repos": 27, "site_admin": false, "subscriptions_url": "https://api.github.com/users/liushuaikobe/subscriptions", "gravatar_id": "", "hireable": true, "id": 2098020, "followers_url": "https://api.github.com/users/liushuaikobe/followers", "following_url": "https://api.github.com/users/liushuaikobe/following{/other_user}", "blog": null, "followers": 131, "location": "Hangzhou, China", "type": "User", "email": "liushuaikobe@gmail.com", "bio": null, "gists_url": "https://api.github.com/users/liushuaikobe/gists{/gist_id}", "company": "AliExpress", "events_url": "https://api.github.com/users/liushuaikobe/events{/privacy}", "html_url": "https://github.com/liushuaikobe", "updated_at": "2016-04-21T09:59:09Z", "received_events_url": "https://api.github.com/users/liushuaikobe/received_events", "starred_url": "https://api.github.com/users/liushuaikobe/starred{/owner}{/repo}", "public_gists": 12, "name": "Shuai Liu", "organizations_url": "https://api.github.com/users/liushuaikobe/orgs", "url": "https://api.github.com/users/liushuaikobe", "created_at": "2012-08-05T11:03:52Z", "avatar_url": "https://avatars.githubusercontent.com/u/2098020?v=3", "repos_url": "https://api.github.com/users/liushuaikobe/repos", "following": 99, "login": "liushuaikobe"}, {"public_repos": 31, "site_admin": false, "subscriptions_url": "https://api.github.com/users/jiacai2050/subscriptions", "gravatar_id": "", "hireable": true, "id": 3848910, "followers_url": "https://api.github.com/users/jiacai2050/followers", "following_url": "https://api.github.com/users/jiacai2050/following{/other_user}", "blog": "http://liujiacai.net/", "followers": 108, "location": "Hangzhou, China", "type": "User", "email": null, "bio": null, "gists_url": "https://api.github.com/users/jiacai2050/gists{/gist_id}", "company": null, "events_url": "https://api.github.com/users/jiacai2050/events{/privacy}", "html_url": "https://github.com/jiacai2050", "updated_at": "2016-05-01T22:18:37Z", "received_events_url": "https://api.github.com/users/jiacai2050/received_events", "starred_url": "https://api.github.com/users/jiacai2050/starred{/owner}{/repo}", "public_gists": 11, "name": "Jiacai Liu", "organizations_url": "https://api.github.com/users/jiacai2050/orgs", "url": "https://api.github.com/users/jiacai2050", "created_at": "2013-03-13T01:33:15Z", "avatar_url": "https://avatars.githubusercontent.com/u/3848910?v=3", "repos_url": "https://api.github.com/users/jiacai2050/repos", "following": 35, "login": "jiacai2050"}, {"public_repos": 56, "site_admin": false, "subscriptions_url": "https://api.github.com/users/elrrrrrrr/subscriptions", "gravatar_id": "", "hireable": null, "id": 5574625, "followers_url": "https://api.github.com/users/elrrrrrrr/followers", "following_url": "https://api.github.com/users/elrrrrrrr/following{/other_user}", "blog": null, "followers": 104, "location": "Hangzhou || Shanghai", "type": "User", "email": "elrrrrrrr@gmail.com", "bio": null, "gists_url": "https://api.github.com/users/elrrrrrrr/gists{/gist_id}", "company": "alipay.com", "events_url": "https://api.github.com/users/elrrrrrrr/events{/privacy}", "html_url": "https://github.com/elrrrrrrr", "updated_at": "2016-05-09T09:01:52Z", "received_events_url": "https://api.github.com/users/elrrrrrrr/received_events", "starred_url": "https://api.github.com/users/elrrrrrrr/starred{/owner}{/repo}", "public_gists": 39, "name": "elrrrrrrr", "organizations_url": "https://api.github.com/users/elrrrrrrr/orgs", "url": "https://api.github.com/users/elrrrrrrr", "created_at": "2013-09-30T08:37:30Z", "avatar_url": "https://avatars.githubusercontent.com/u/5574625?v=3", "repos_url": "https://api.github.com/users/elrrrrrrr/repos", "following": 111, "login": "elrrrrrrr"}, {"public_repos": 35, "site_admin": false, "subscriptions_url": "https://api.github.com/users/shijinkui/subscriptions", "gravatar_id": "", "hireable": null, "id": 648508, "followers_url": "https://api.github.com/users/shijinkui/followers", "following_url": "https://api.github.com/users/shijinkui/following{/other_user}", "blog": "http://www.pusuo.net", "followers": 103, "location": "hangzhou", "type": "User", "email": null, "bio": null, "gists_url": "https://api.github.com/users/shijinkui/gists{/gist_id}", "company": null, "events_url": "https://api.github.com/users/shijinkui/events{/privacy}", "html_url": "https://github.com/shijinkui", "updated_at": "2016-05-11T15:50:58Z", "received_events_url": "https://api.github.com/users/shijinkui/received_events", "starred_url": "https://api.github.com/users/shijinkui/starred{/owner}{/repo}", "public_gists": 73, "name": "shi jinkui", "organizations_url": "https://api.github.com/users/shijinkui/orgs", "url": "https://api.github.com/users/shijinkui", "created_at": "2011-03-03T07:02:36Z", "avatar_url": "https://avatars.githubusercontent.com/u/648508?v=3", "repos_url": "https://api.github.com/users/shijinkui/repos", "following": 78, "login": "shijinkui"}, {"public_repos": 4, "site_admin": false, "subscriptions_url": "https://api.github.com/users/hexianmao/subscriptions", "gravatar_id": "", "hireable": null, "id": 1768049, "followers_url": "https://api.github.com/users/hexianmao/followers", "following_url": "https://api.github.com/users/hexianmao/following{/other_user}", "blog": null, "followers": 90, "location": "Hangzhou", "type": "User", "email": "xianmao.hexm@alibaba-inc.com", "bio": null, "gists_url": "https://api.github.com/users/hexianmao/gists{/gist_id}", "company": "Alibaba", "events_url": "https://api.github.com/users/hexianmao/events{/privacy}", "html_url": "https://github.com/hexianmao", "updated_at": "2016-04-30T12:25:49Z", "received_events_url": "https://api.github.com/users/hexianmao/received_events", "starred_url": "https://api.github.com/users/hexianmao/starred{/owner}{/repo}", "public_gists": 0, "name": "\u8d3a\u8d24\u61cb", "organizations_url": "https://api.github.com/users/hexianmao/orgs", "url": "https://api.github.com/users/hexianmao", "created_at": "2012-05-23T03:03:03Z", "avatar_url": "https://avatars.githubusercontent.com/u/1768049?v=3", "repos_url": "https://api.github.com/users/hexianmao/repos", "following": 0, "login": "hexianmao"}, {"public_repos": 26, "site_admin": false, "subscriptions_url": "https://api.github.com/users/yeungeek/subscriptions", "gravatar_id": "", "hireable": null, "id": 271539, "followers_url": "https://api.github.com/users/yeungeek/followers", "following_url": "https://api.github.com/users/yeungeek/following{/other_user}", "blog": "http://yeungeek.com", "followers": 89, "location": "hangzhou", "type": "User", "email": "yangjian0410@gmail.com", "bio": null, "gists_url": "https://api.github.com/users/yeungeek/gists{/gist_id}", "company": "Huaban", "events_url": "https://api.github.com/users/yeungeek/events{/privacy}", "html_url": "https://github.com/yeungeek", "updated_at": "2016-04-22T10:18:44Z", "received_events_url": "https://api.github.com/users/yeungeek/received_events", "starred_url": "https://api.github.com/users/yeungeek/starred{/owner}{/repo}", "public_gists": 3, "name": "yeungeek", "organizations_url": "https://api.github.com/users/yeungeek/orgs", "url": "https://api.github.com/users/yeungeek", "created_at": "2010-05-09T08:16:29Z", "avatar_url": "https://avatars.githubusercontent.com/u/271539?v=3", "repos_url": "https://api.github.com/users/yeungeek/repos", "following": 100, "login": "yeungeek"}, {"public_repos": 24, "site_admin": false, "subscriptions_url": "https://api.github.com/users/teaey/subscriptions", "gravatar_id": "", "hireable": null, "id": 3061252, "followers_url": "https://api.github.com/users/teaey/followers", "following_url": "https://api.github.com/users/teaey/following{/other_user}", "blog": "http://teaey.cn", "followers": 86, "location": "Hangzhou, China", "type": "User", "email": "masfay@me.com", "bio": null, "gists_url": "https://api.github.com/users/teaey/gists{/gist_id}", "company": "Alibaba", "events_url": "https://api.github.com/users/teaey/events{/privacy}", "html_url": "https://github.com/teaey", "updated_at": "2016-05-10T09:15:09Z", "received_events_url": "https://api.github.com/users/teaey/received_events", "starred_url": "https://api.github.com/users/teaey/starred{/owner}{/repo}", "public_gists": 0, "name": "Wu.XiaoFei", "organizations_url": "https://api.github.com/users/teaey/orgs", "url": "https://api.github.com/users/teaey", "created_at": "2012-12-17T08:18:15Z", "avatar_url": "https://avatars.githubusercontent.com/u/3061252?v=3", "repos_url": "https://api.github.com/users/teaey/repos", "following": 18, "login": "teaey"}, {"public_repos": 10, "site_admin": false, "subscriptions_url": "https://api.github.com/users/kiminotes/subscriptions", "gravatar_id": "", "hireable": null, "id": 437477, "followers_url": "https://api.github.com/users/kiminotes/followers", "following_url": "https://api.github.com/users/kiminotes/following{/other_user}", "blog": "http://www.kiminotes.net", "followers": 84, "location": "hangzhou, zhejiang, china", "type": "User", "email": "kiminotes.lv@gmail.com", "bio": null, "gists_url": "https://api.github.com/users/kiminotes/gists{/gist_id}", "company": "alibaba.com", "events_url": "https://api.github.com/users/kiminotes/events{/privacy}", "html_url": "https://github.com/kiminotes", "updated_at": "2016-05-10T09:59:09Z", "received_events_url": "https://api.github.com/users/kiminotes/received_events", "starred_url": "https://api.github.com/users/kiminotes/starred{/owner}{/repo}", "public_gists": 0, "name": "kimi", "organizations_url": "https://api.github.com/users/kiminotes/orgs", "url": "https://api.github.com/users/kiminotes", "created_at": "2010-10-13T03:57:07Z", "avatar_url": "https://avatars.githubusercontent.com/u/437477?v=3", "repos_url": "https://api.github.com/users/kiminotes/repos", "following": 28, "login": "kiminotes"}, {"public_repos": 8, "site_admin": false, "subscriptions_url": "https://api.github.com/users/zephyrleaves/subscriptions", "gravatar_id": "", "hireable": null, "id": 363180, "followers_url": "https://api.github.com/users/zephyrleaves/followers", "following_url": "https://api.github.com/users/zephyrleaves/following{/other_user}", "blog": "http://blog.zephyrleaves.net/", "followers": 76, "location": "hangzhou,China", "type": "User", "email": "zephyrleaves@gmail.com", "bio": null, "gists_url": "https://api.github.com/users/zephyrleaves/gists{/gist_id}", "company": "taobao.com", "events_url": "https://api.github.com/users/zephyrleaves/events{/privacy}", "html_url": "https://github.com/zephyrleaves", "updated_at": "2016-02-26T23:21:04Z", "received_events_url": "https://api.github.com/users/zephyrleaves/received_events", "starred_url": "https://api.github.com/users/zephyrleaves/starred{/owner}{/repo}", "public_gists": 0, "name": "\u6587\u901a|Kevin.Huang", "organizations_url": "https://api.github.com/users/zephyrleaves/orgs", "url": "https://api.github.com/users/zephyrleaves", "created_at": "2010-08-13T08:12:47Z", "avatar_url": "https://avatars.githubusercontent.com/u/363180?v=3", "repos_url": "https://api.github.com/users/zephyrleaves/repos", "following": 6, "login": "zephyrleaves"}, {"public_repos": 54, "site_admin": false, "subscriptions_url": "https://api.github.com/users/MummyDing/subscriptions", "gravatar_id": "", "hireable": null, "id": 7663362, "followers_url": "https://api.github.com/users/MummyDing/followers", "following_url": "https://api.github.com/users/MummyDing/following{/other_user}", "blog": "http://blog.csdn.net/mummyding", "followers": 75, "location": "Hangzhou,China", "type": "User", "email": "MummyDing@outlook.com", "bio": null, "gists_url": "https://api.github.com/users/MummyDing/gists{/gist_id}", "company": "Netease", "events_url": "https://api.github.com/users/MummyDing/events{/privacy}", "html_url": "https://github.com/MummyDing", "updated_at": "2016-05-09T03:38:53Z", "received_events_url": "https://api.github.com/users/MummyDing/received_events", "starred_url": "https://api.github.com/users/MummyDing/starred{/owner}{/repo}", "public_gists": 0, "name": "MummyDing", "organizations_url": "https://api.github.com/users/MummyDing/orgs", "url": "https://api.github.com/users/MummyDing", "created_at": "2014-05-22T01:22:37Z", "avatar_url": "https://avatars.githubusercontent.com/u/7663362?v=3", "repos_url": "https://api.github.com/users/MummyDing/repos", "following": 26, "login": "MummyDing"}, {"public_repos": 22, "site_admin": false, "subscriptions_url": "https://api.github.com/users/ashqal/subscriptions", "gravatar_id": "", "hireable": null, "id": 5126517, "followers_url": "https://api.github.com/users/ashqal/followers", "following_url": "https://api.github.com/users/ashqal/following{/other_user}", "blog": null, "followers": 74, "location": "Hangzhou", "type": "User", "email": "ashqalcn@gmail.com", "bio": null, "gists_url": "https://api.github.com/users/ashqal/gists{/gist_id}", "company": "Netease", "events_url": "https://api.github.com/users/ashqal/events{/privacy}", "html_url": "https://github.com/ashqal", "updated_at": "2016-05-06T12:09:31Z", "received_events_url": "https://api.github.com/users/ashqal/received_events", "starred_url": "https://api.github.com/users/ashqal/starred{/owner}{/repo}", "public_gists": 1, "name": "Asha", "organizations_url": "https://api.github.com/users/ashqal/orgs", "url": "https://api.github.com/users/ashqal", "created_at": "2013-07-31T05:20:59Z", "avatar_url": "https://avatars.githubusercontent.com/u/5126517?v=3", "repos_url": "https://api.github.com/users/ashqal/repos", "following": 18, "login": "ashqal"}]